procrustes/__init__.py
procrustes/base.html
procrustes/main.html
procrustes/search.html
procrustes/styles.css
procrustes/css/theme.css
mkdocs_procrustes-0.0.1.dist-info/LICENSE
mkdocs_procrustes-0.0.1.dist-info/METADATA
mkdocs_procrustes-0.0.1.dist-info/WHEEL
mkdocs_procrustes-0.0.1.dist-info/entry_points.txt
mkdocs_procrustes-0.0.1.dist-info/top_level.txt
mkdocs_procrustes-0.0.1.dist-info/RECORD
