Metadata-Version: 2.1
Name: mkdocs-procrustes
Version: 0.0.1
Summary: A Vanilla-framework based theme
Home-page: https://github.com/evilnick/procrustes
Author: Nick Veitch
Author-email: nick.veitch@canonical.com
License-File: LICENSE
